setup.py
recon/__init__.py
recon.egg-info/PKG-INFO
recon.egg-info/SOURCES.txt
recon.egg-info/dependency_links.txt
recon.egg-info/top_level.txt