Metadata-Version: 1.0
Name: recon
Version: 0.0.1
Summary: Recon is a Trigger-based replacement for RANCID.
Home-page: https://github.com/trigger/trigger
Author: Jathan McCollum
Author-email: jathan@gmail.com
License: BSD
Platform: UNKNOWN
